websauna-1.0a13-py3.7-nspkg.pth
websauna/compat/__init__.py
websauna/compat/typing.py
websauna/conf/base.ini
websauna/conf/development.ini
websauna/conf/production.ini
websauna/conf/secrets.ini
websauna/conf/test-secrets.ini
websauna/conf/test.ini
websauna/conf/travis.ini
websauna/system/__init__.py
websauna/system/admin/__init__.py
websauna/system/admin/admin.py
websauna/system/admin/events.py
websauna/system/admin/filters.py
websauna/system/admin/interfaces.py
websauna/system/admin/menu.py
websauna/system/admin/modeladmin.py
websauna/system/admin/subscribers.py
websauna/system/admin/utils.py
websauna/system/admin/views.py
websauna/system/admin/templates/admin/admin.html
websauna/system/admin/templates/admin/base.html
websauna/system/admin/templates/admin/base_panel.html
websauna/system/admin/templates/admin/breadcrumbs.html
websauna/system/admin/templates/admin/model_panel.html
websauna/system/admin/templates/admin/menu/entry.html
websauna/system/admin/templates/admin/menu/navbar.html
websauna/system/admin/templates/admin/menu/submenu.html
websauna/system/auth/__init__.py
websauna/system/auth/authentication.py
websauna/system/auth/policy.py
websauna/system/auth/principals.py
websauna/system/auth/subscribers.py
websauna/system/auth/tweens.py
websauna/system/core/__init__.py
websauna/system/core/breadcrumbs.py
websauna/system/core/events.py
websauna/system/core/interfaces.py
websauna/system/core/loggingcapture.py
websauna/system/core/messages.py
websauna/system/core/panel.py
websauna/system/core/redis.py
websauna/system/core/render.py
websauna/system/core/root.py
websauna/system/core/route.py
websauna/system/core/session.py
websauna/system/core/simpleroute.py
websauna/system/core/sitemap.py
websauna/system/core/templatecontext.py
websauna/system/core/traversal.py
websauna/system/core/utils.py
websauna/system/core/vars.py
websauna/system/core/viewconfig.py
websauna/system/core/templates/core/badcsrftoken.html
websauna/system/core/templates/core/forbidden.html
websauna-1.0a13.dist-info/LICENSE.txt
websauna-1.0a13.dist-info/METADATA
websauna-1.0a13.dist-info/WHEEL
websauna-1.0a13.dist-info/entry_points.txt
websauna-1.0a13.dist-info/namespace_packages.txt
websauna-1.0a13.dist-info/top_level.txt
websauna-1.0a13.dist-info/RECORD
