Metadata-Version: 2.1
Name: websauna
Version: 1.0a13
Summary: Websauna is a full stack Python web framework for building web services and back offices with admin interface and sign up process.
Home-page: https://websauna.org
Author: Mikko Ohtamaa
Author-email: mikko@opensourcehacker.com
License: MIT
Keywords: sqlalchemy postgresql pyramid pytest websauna
Platform: UNKNOWN
Classifier: Development Status :: 3 - Alpha
Classifier: Framework :: Pyramid
Classifier: Intended Audience :: Developers
Classifier: License :: OSI Approved :: MIT License
Classifier: Programming Language :: Python :: 3
Classifier: Programming Language :: Python :: 3.5
Classifier: Programming Language :: Python :: 3.6
Classifier: Programming Language :: Python :: 3.7
Classifier: Programming Language :: Python :: Implementation :: CPython
Classifier: Topic :: Internet :: WWW/HTTP
Classifier: Topic :: Internet :: WWW/HTTP :: Dynamic Content
Classifier: Topic :: Internet :: WWW/HTTP :: WSGI :: Application
Classifier: Topic :: Internet :: WWW/HTTP :: WSGI
Classifier: Topic :: Software Development :: Libraries :: Application Frameworks
Requires-Python: >=3.5.2
Provides-Extra: dev
Provides-Extra: celery
Provides-Extra: test
Provides-Extra: docs
Provides-Extra: utils
Provides-Extra: notebook
